LICENSE.txt
MANIFEST.in
README.rst
requirements.txt
setup.py
redock/__init__.py
redock/api.py
redock/base.py
redock/bootstrap.py
redock/cli.py
redock/tests.py
redock/utils.py
redock.egg-info/PKG-INFO
redock.egg-info/SOURCES.txt
redock.egg-info/dependency_links.txt
redock.egg-info/entry_points.txt
redock.egg-info/requires.txt
redock.egg-info/top_level.txt