Metadata-Version: 1.0
Name: redock
Version: 0.5.8
Summary: Human friendly wrapper around Docker
Home-page: https://github.com/xolox/python-redock
Author: Peter Odding
Author-email: peter@peterodding.com
License: UNKNOWN
Platform: UNKNOWN
